Workbook

Sheet Registre des risques
A1: Registre des risques - Migration de la messagerie vers une solution cloud
A2: De Sousa Nunes Alessandro - CFC 3
A4: ID | B4: Risque | C4: Catégorie | D4: Cause | E4: Conséquence | F4: Proba. (1-5) | G4: Impact (1-5) | H4: Score | I4: Niveau | J4: Rang | K4: Stratégie | L4: Mesure préventive | M4: Responsable
A5: R1 | B5: Perte ou corruption de courriels pendant la migration des boîtes | C5: Technique | D5: Boîtes volumineuses, coupure pendant le transfert, outil de migration mal paramétré | E5: Perte d'historique client, problème légal (conservation des pièces 10 ans) | F5: 3 | G5: 5 | H5: =F5*G5 -> 15 | I5: =IF(H5>=12,"Critique",IF(H5>=8,"Élevé",IF(H5>=4,"Moyen","Faible"))) -> Critique | J5: =COUNTIF($H$5:$H$14,">"&H5)+COUNTIFS($H$5:$H$14,H5,$G$5:$G$14,">"&G5)+COUNTIFS($H$5:H5,H5,$G$5:G5,G5) -> 1 | K5: Réduire | L5: Sauvegarde complète avant migration, migration pilote sur 3 boîtes, contrôle du nombre d'éléments avant/après | M5: Admin système
A6: R2 | B6: Messagerie indisponible le jour du basculement | C6: Technique | D6: Basculement des enregistrements DNS (MX), synchronisation incomplète | E6: Courriels clients non reçus, activité bloquée | F6: 3 | G6: 4 | H6: =F6*G6 -> 12 | I6: =IF(H6>=12,"Critique",IF(H6>=8,"Élevé",IF(H6>=4,"Moyen","Faible"))) -> Critique | J6: =COUNTIF($H$5:$H$14,">"&H6)+COUNTIFS($H$5:$H$14,H6,$G$5:$G$14,">"&G6)+COUNTIFS($H$5:H6,H6,$G$5:G6,G6) -> 2 | K6: Réduire | L6: Basculement un vendredi soir, TTL DNS abaissé 48 h avant, plan de retour arrière | M6: Admin système
A7: R3 | B7: Utilisateurs perdus avec le nouvel outil (résistance au changement) | C7: Humain | D7: Changement d'interface, pas de formation, habitudes | E7: Baisse de productivité, nombreux appels au support, rejet du projet | F7: 4 | G7: 3 | H7: =F7*G7 -> 12 | I7: =IF(H7>=12,"Critique",IF(H7>=8,"Élevé",IF(H7>=4,"Moyen","Faible"))) -> Critique | J7: =COUNTIF($H$5:$H$14,">"&H7)+COUNTIFS($H$5:$H$14,H7,$G$5:$G$14,">"&G7)+COUNTIFS($H$5:H7,H7,$G$5:G7,G7) -> 3 | K7: Réduire | L7: Communication dès le lancement, formation courte, guide d'une page, référents par service | M7: Chef de projet
A8: R4 | B8: Dépassement du budget (licences, prestations) | C8: Organisationnel | D8: Nombre de licences mal estimé, heures de support externe en plus | E8: Budget dépassé, arbitrage de la direction | F8: 3 | G8: 3 | H8: =F8*G8 -> 9 | I8: =IF(H8>=12,"Critique",IF(H8>=8,"Élevé",IF(H8>=4,"Moyen","Faible"))) -> Élevé | J8: =COUNTIF($H$5:$H$14,">"&H8)+COUNTIFS($H$5:$H$14,H8,$G$5:$G$14,">"&G8)+COUNTIFS($H$5:H8,H8,$G$5:G8,G8) -> 5 | K8: Réduire | L8: Inventaire exact des comptes, devis fermes, réserve de 10 % | M8: Chef de projet
A9: R5 | B9: Incompatibilité avec des appareils ou logiciels qui envoient des e-mails | C9: Technique | D9: Scanner, imprimante multifonction, logiciel métier utilisant l'ancien serveur SMTP | E9: Envois automatiques bloqués (scans, factures) | F9: 3 | G9: 3 | H9: =F9*G9 -> 9 | I9: =IF(H9>=12,"Critique",IF(H9>=8,"Élevé",IF(H9>=4,"Moyen","Faible"))) -> Élevé | J9: =COUNTIF($H$5:$H$14,">"&H9)+COUNTIFS($H$5:$H$14,H9,$G$5:$G$14,">"&G9)+COUNTIFS($H$5:H9,H9,$G$5:G9,G9) -> 6 | K9: Réduire | L9: Inventaire des appareils qui envoient des e-mails, tests avant le basculement | M9: Admin système
A10: R6 | B10: Mauvaise configuration de sécurité (SPF, DKIM, MFA) | C10: Technique | D10: Paramétrage incomplet du nouveau domaine | E10: Courriels classés en spam, risque de phishing et d'usurpation | F10: 2 | G10: 5 | H10: =F10*G10 -> 10 | I10: =IF(H10>=12,"Critique",IF(H10>=8,"Élevé",IF(H10>=4,"Moyen","Faible"))) -> Élevé | J10: =COUNTIF($H$5:$H$14,">"&H10)+COUNTIFS($H$5:$H$14,H10,$G$5:$G$14,">"&G10)+COUNTIFS($H$5:H10,H10,$G$5:G10,G10) -> 4 | K10: Réduire | L10: Checklist de sécurité, activation MFA, contrôle avec un outil de test DNS | M10: Admin système
A11: R7 | B11: Absence de la personne clé (admin système) | C11: Humain | D11: Maladie, vacances, départ | E11: Projet bloqué ou retardé | F11: 2 | G11: 3 | H11: =F11*G11 -> 6 | I11: =IF(H11>=12,"Critique",IF(H11>=8,"Élevé",IF(H11>=4,"Moyen","Faible"))) -> Moyen | J11: =COUNTIF($H$5:$H$14,">"&H11)+COUNTIFS($H$5:$H$14,H11,$G$5:$G$14,">"&G11)+COUNTIFS($H$5:H11,H11,$G$5:G11,G11) -> 9 | K11: Réduire | L11: Documentation des étapes, binôme avec un deuxième technicien | M11: Chef de projet
A12: R8 | B12: Mauvaise configuration DNS (MX) au basculement | C12: Technique | D12: Erreur de saisie, propagation DNS | E12: Courriels rejetés ou perdus pendant plusieurs heures | F12: 2 | G12: 4 | H12: =F12*G12 -> 8 | I12: =IF(H12>=12,"Critique",IF(H12>=8,"Élevé",IF(H12>=4,"Moyen","Faible"))) -> Élevé | J12: =COUNTIF($H$5:$H$14,">"&H12)+COUNTIFS($H$5:$H$14,H12,$G$5:$G$14,">"&G12)+COUNTIFS($H$5:H12,H12,$G$5:G12,G12) -> 7 | K12: Réduire | L12: Double contrôle des enregistrements, test d'envoi externe juste après la modification | M12: Admin système
A13: R9 | B13: Non-conformité à la protection des données (nLPD) | C13: Organisationnel | D13: Lieu d'hébergement des données non vérifié, pas d'analyse du contrat | E13: Sanction, perte de confiance des clients | F13: 2 | G13: 4 | H13: =F13*G13 -> 8 | I13: =IF(H13>=12,"Critique",IF(H13>=8,"Élevé",IF(H13>=4,"Moyen","Faible"))) -> Élevé | J13: =COUNTIF($H$5:$H$14,">"&H13)+COUNTIFS($H$5:$H$14,H13,$G$5:$G$14,">"&G13)+COUNTIFS($H$5:H13,H13,$G$5:G13,G13) -> 8 | K13: Transférer / réduire | L13: Choisir un hébergement en Suisse ou UE, faire valider le contrat par la direction | M13: Direction
A14: R10 | B14: Bande passante insuffisante pendant la synchronisation | C14: Technique | D14: Volume de données important, connexion partagée | E14: Migration plus lente, internet ralenti pour les utilisateurs | F14: 3 | G14: 2 | H14: =F14*G14 -> 6 | I14: =IF(H14>=12,"Critique",IF(H14>=8,"Élevé",IF(H14>=4,"Moyen","Faible"))) -> Moyen | J14: =COUNTIF($H$5:$H$14,">"&H14)+COUNTIFS($H$5:$H$14,H14,$G$5:$G$14,">"&G14)+COUNTIFS($H$5:H14,H14,$G$5:G14,G14) -> 10 | K14: Accepter | L14: Migration la nuit et le week-end, suivi du débit | M14: Admin système
A16: Score = probabilité x impact. Niveau : 12 et plus = critique, 8 à 11 = élevé, 4 à 7 = moyen, 1 à 3 = faible. En cas d'égalité de score, le risque avec le plus grand impact est classé avant.

Sheet Matrice P-I
A1: Matrice probabilité / impact
A2: De Sousa Nunes Alessandro - CFC 3
B4: Probabilité | C4: 5 - Très probable | D4: {=_xlfn.TEXTJOIN(" ",TRUE,IF(('Registre des risques'!$F$5:$F$14=5)*('Registre des risques'!$G$5:$G$14=1),'Registre des risques'!$A$5:$A$14,""))} | E4: {=_xlfn.TEXTJOIN(" ",TRUE,IF(('Registre des risques'!$F$5:$F$14=5)*('Registre des risques'!$G$5:$G$14=2),'Registre des risques'!$A$5:$A$14,""))} | F4: {=_xlfn.TEXTJOIN(" ",TRUE,IF(('Registre des risques'!$F$5:$F$14=5)*('Registre des risques'!$G$5:$G$14=3),'Registre des risques'!$A$5:$A$14,""))} | G4: {=_xlfn.TEXTJOIN(" ",TRUE,IF(('Registre des risques'!$F$5:$F$14=5)*('Registre des risques'!$G$5:$G$14=4),'Registre des risques'!$A$5:$A$14,""))} | H4: {=_xlfn.TEXTJOIN(" ",TRUE,IF(('Registre des risques'!$F$5:$F$14=5)*('Registre des risques'!$G$5:$G$14=5),'Registre des risques'!$A$5:$A$14,""))} | J4: Légende
C5: 4 - Probable | D5: {=_xlfn.TEXTJOIN(" ",TRUE,IF(('Registre des risques'!$F$5:$F$14=4)*('Registre des risques'!$G$5:$G$14=1),'Registre des risques'!$A$5:$A$14,""))} | E5: {=_xlfn.TEXTJOIN(" ",TRUE,IF(('Registre des risques'!$F$5:$F$14=4)*('Registre des risques'!$G$5:$G$14=2),'Registre des risques'!$A$5:$A$14,""))} | F5: {=_xlfn.TEXTJOIN(" ",TRUE,IF(('Registre des risques'!$F$5:$F$14=4)*('Registre des risques'!$G$5:$G$14=3),'Registre des risques'!$A$5:$A$14,""))} -> R3 | G5: {=_xlfn.TEXTJOIN(" ",TRUE,IF(('Registre des risques'!$F$5:$F$14=4)*('Registre des risques'!$G$5:$G$14=4),'Registre des risques'!$A$5:$A$14,""))} | H5: {=_xlfn.TEXTJOIN(" ",TRUE,IF(('Registre des risques'!$F$5:$F$14=4)*('Registre des risques'!$G$5:$G$14=5),'Registre des risques'!$A$5:$A$14,""))} | K5: Critique (12-25)
C6: 3 - Possible | D6: {=_xlfn.TEXTJOIN(" ",TRUE,IF(('Registre des risques'!$F$5:$F$14=3)*('Registre des risques'!$G$5:$G$14=1),'Registre des risques'!$A$5:$A$14,""))} | E6: {=_xlfn.TEXTJOIN(" ",TRUE,IF(('Registre des risques'!$F$5:$F$14=3)*('Registre des risques'!$G$5:$G$14=2),'Registre des risques'!$A$5:$A$14,""))} -> R10 | F6: {=_xlfn.TEXTJOIN(" ",TRUE,IF(('Registre des risques'!$F$5:$F$14=3)*('Registre des risques'!$G$5:$G$14=3),'Registre des risques'!$A$5:$A$14,""))} -> R4 R5 | G6: {=_xlfn.TEXTJOIN(" ",TRUE,IF(('Registre des risques'!$F$5:$F$14=3)*('Registre des risques'!$G$5:$G$14=4),'Registre des risques'!$A$5:$A$14,""))} -> R2 | H6: {=_xlfn.TEXTJOIN(" ",TRUE,IF(('Registre des risques'!$F$5:$F$14=3)*('Registre des risques'!$G$5:$G$14=5),'Registre des risques'!$A$5:$A$14,""))} -> R1 | K6: Élevé (8-11)
C7: 2 - Peu probable | D7: {=_xlfn.TEXTJOIN(" ",TRUE,IF(('Registre des risques'!$F$5:$F$14=2)*('Registre des risques'!$G$5:$G$14=1),'Registre des risques'!$A$5:$A$14,""))} | E7: {=_xlfn.TEXTJOIN(" ",TRUE,IF(('Registre des risques'!$F$5:$F$14=2)*('Registre des risques'!$G$5:$G$14=2),'Registre des risques'!$A$5:$A$14,""))} | F7: {=_xlfn.TEXTJOIN(" ",TRUE,IF(('Registre des risques'!$F$5:$F$14=2)*('Registre des risques'!$G$5:$G$14=3),'Registre des risques'!$A$5:$A$14,""))} -> R7 | G7: {=_xlfn.TEXTJOIN(" ",TRUE,IF(('Registre des risques'!$F$5:$F$14=2)*('Registre des risques'!$G$5:$G$14=4),'Registre des risques'!$A$5:$A$14,""))} -> R8 R9 | H7: {=_xlfn.TEXTJOIN(" ",TRUE,IF(('Registre des risques'!$F$5:$F$14=2)*('Registre des risques'!$G$5:$G$14=5),'Registre des risques'!$A$5:$A$14,""))} -> R6 | K7: Moyen (4-7)
C8: 1 - Rare | D8: {=_xlfn.TEXTJOIN(" ",TRUE,IF(('Registre des risques'!$F$5:$F$14=1)*('Registre des risques'!$G$5:$G$14=1),'Registre des risques'!$A$5:$A$14,""))} | E8: {=_xlfn.TEXTJOIN(" ",TRUE,IF(('Registre des risques'!$F$5:$F$14=1)*('Registre des risques'!$G$5:$G$14=2),'Registre des risques'!$A$5:$A$14,""))} | F8: {=_xlfn.TEXTJOIN(" ",TRUE,IF(('Registre des risques'!$F$5:$F$14=1)*('Registre des risques'!$G$5:$G$14=3),'Registre des risques'!$A$5:$A$14,""))} | G8: {=_xlfn.TEXTJOIN(" ",TRUE,IF(('Registre des risques'!$F$5:$F$14=1)*('Registre des risques'!$G$5:$G$14=4),'Registre des risques'!$A$5:$A$14,""))} | H8: {=_xlfn.TEXTJOIN(" ",TRUE,IF(('Registre des risques'!$F$5:$F$14=1)*('Registre des risques'!$G$5:$G$14=5),'Registre des risques'!$A$5:$A$14,""))} | K8: Faible (1-3)
D10: 1 - Négligeable | E10: 2 - Mineur | F10: 3 - Moyen | G10: 4 - Majeur | H10: 5 - Grave
D11: Impact
C13: Les identifiants de chaque case sont calculés automatiquement à partir du registre (onglet Registre des risques).

Sheet Échelles
A1: Échelles d'évaluation utilisées
A3: Note | B3: Probabilité | C3: Impact
A4: 1 | B4: Rare : moins de 10 % de chance | C4: Négligeable : gêne mineure, aucun retard
A5: 2 | B5: Peu probable : 10 à 30 % | C5: Mineur : retard de moins d'un jour, petit surcoût
A6: 3 | B6: Possible : 30 à 50 % | C6: Moyen : retard de quelques jours ou gêne pour plusieurs utilisateurs
A7: 4 | B7: Probable : 50 à 80 % | C7: Majeur : activité perturbée, retard d'une semaine, surcoût important
A8: 5 | B8: Très probable : plus de 80 % | C8: Grave : perte de données, arrêt de l'activité ou problème légal
