Workbook

Sheet Budget
A1: Budget prévisionnel - Mise en place d'un wiki interne
A2: De Sousa Nunes Alessandro - CFC 3
A4: Lot de travail | B4: Jours | C4: Chef de projet (h) | D4: Admin système (h) | E4: Développeur (h) | F4: Référent métier (h) | G4: Coût main-d'oeuvre (CHF) | H4: Autres coûts (CHF) | I4: Total (CHF)
A5: Tarif horaire (CHF) | C5: 110 | D5: 100 | E5: 105 | F5: 90
A6: L1 - Cadrage et lancement | B6: J1 | C6: 8 | F6: 4 | G6: =SUMPRODUCT(C6:F6,$C$5:$F$5) -> 1240 | I6: =G6+H6 -> 1240
A7: L2 - Installation du serveur et du wiki | B7: J1-J2 | D7: 16 | G7: =SUMPRODUCT(C7:F7,$C$5:$F$5) -> 1600 | I7: =G7+H7 -> 1600
A8: L3 - Configuration (droits, connexion des comptes) | B8: J2-J3 | D8: 8 | E8: 8 | G8: =SUMPRODUCT(C8:F8,$C$5:$F$5) -> 1640 | I8: =G8+H8 -> 1640
A9: L4 - Reprise des documents existants | B9: J3-J4 | E9: 8 | F9: 12 | G9: =SUMPRODUCT(C9:F9,$C$5:$F$5) -> 1920 | I9: =G9+H9 -> 1920
A10: L5 - Tests et recette | B10: J4-J5 | C10: 6 | D10: 4 | F10: 4 | G10: =SUMPRODUCT(C10:F10,$C$5:$F$5) -> 1420 | I10: =G10+H10 -> 1420
A11: L6 - Formation des utilisateurs | B11: J5 | C11: 4 | F11: 4 | G11: =SUMPRODUCT(C11:F11,$C$5:$F$5) -> 800 | I11: =G11+H11 -> 800
A12: L7 - Pilotage et reporting | B12: J1-J5 | C12: 12 | G12: =SUMPRODUCT(C12:F12,$C$5:$F$5) -> 1320 | I12: =G12+H12 -> 1320
A13: L8 - Machine virtuelle et nom de domaine (1re année) | B13: J1 | G13: =SUMPRODUCT(C13:F13,$C$5:$F$5) -> 0 | H13: 500 | I13: =G13+H13 -> 500
A14: Sous-total | C14: =SUM(C6:C13) -> 30 | D14: =SUM(D6:D13) -> 28 | E14: =SUM(E6:E13) -> 16 | F14: =SUM(F6:F13) -> 24 | G14: =SUM(G6:G13) -> 9940 | H14: =SUM(H6:H13) -> 500 | I14: =SUM(I6:I13) -> 10440
A15: Réserve pour imprévus (10 %) | I15: =ROUND(I14*0.1,0) -> 1044
A16: Budget total du projet | I16: =I14+I15 -> 11484
A18: Les coûts sont calculés par formules : heures x tarif horaire de chaque rôle.

Sheet Planning
A1: Planning global (semaine PPE, 5 jours)
A2: De Sousa Nunes Alessandro - CFC 3
A4: Lot de travail | B4: J1 lun | C4: J2 mar | D4: J3 mer | E4: J4 jeu | F4: J5 ven | G4: Responsable
A5: L1 - Cadrage et lancement | G5: Chef de projet
A6: L2 - Installation du serveur et du wiki | G6: Admin système
A7: L3 - Configuration | G7: Admin système / Dév.
A8: L4 - Reprise des documents | G8: Dév. / Référent
A9: L5 - Tests et recette | G9: Chef de projet
A10: L6 - Formation | G10: Chef de projet
A11: L7 - Pilotage et reporting | G11: Chef de projet
A13: Jalons
A14: Plan de projet validé | B14: ◆
A15: Comité de pilotage 1 (rapport n°1) | C15: ◆
A16: Comité de pilotage 2 (rapport n°2) | E16: ◆
A17: Clôture, bilan et REX | F17: ◆

Sheet Suivi
A1: Tableau de bord - suivi des coûts et de l'avancement
A2: De Sousa Nunes Alessandro - CFC 3
A4: Jour | B4: Coût prévu du jour | C4: Coût prévu cumulé | D4: Avancement prévu | E4: Coût réel du jour | F4: Coût réel cumulé | G4: Avancement réel | H4: Écart de coût cumulé | I4: Statut
A5: J1 lun | B5: =Budget!I6+Budget!I7/2+Budget!I13+Budget!I12/5 -> 2804 | C5: =SUM($B$5:B5) -> 2804 | D5: =C5/Budget!$I$14 -> 0.26858238 | E5: 2849 | F5: =IF(E5="",NA(),SUM($E$5:E5)) -> 2849 | G5: 0.27 | H5: =IF(E5="","",F5-C5) -> 45 | I5: =IF(E5="","à compléter",IF(H5>Budget!$I$15,"Alerte : réserve dépassée",IF(H5>0,"Dépassement (dans la réserve)","Dans le budget"))) -> Dépassement (dans la réserve)
A6: J2 mar | B6: =Budget!I7/2+Budget!I8/2+Budget!I12/5 -> 1884 | C6: =SUM($B$5:B6) -> 4688 | D6: =C6/Budget!$I$14 -> 0.44904215 | E6: 1884 | F6: =IF(E6="",NA(),SUM($E$5:E6)) -> 4733 | G6: 0.45 | H6: =IF(E6="","",F6-C6) -> 45 | I6: =IF(E6="","à compléter",IF(H6>Budget!$I$15,"Alerte : réserve dépassée",IF(H6>0,"Dépassement (dans la réserve)","Dans le budget"))) -> Dépassement (dans la réserve)
A7: J3 mer | B7: =Budget!I8/2+Budget!I9/2+Budget!I12/5 -> 2044 | C7: =SUM($B$5:B7) -> 6732 | D7: =C7/Budget!$I$14 -> 0.64482759 | E7: 2064 | F7: =IF(E7="",NA(),SUM($E$5:E7)) -> 6797 | G7: 0.58 | H7: =IF(E7="","",F7-C7) -> 65 | I7: =IF(E7="","à compléter",IF(H7>Budget!$I$15,"Alerte : réserve dépassée",IF(H7>0,"Dépassement (dans la réserve)","Dans le budget"))) -> Dépassement (dans la réserve)
A8: J4 jeu | B8: =Budget!I9/2+Budget!I10/2+Budget!I12/5 -> 1934 | C8: =SUM($B$5:B8) -> 8666 | D8: =C8/Budget!$I$14 -> 0.83007663 | E8: 2334 | F8: =IF(E8="",NA(),SUM($E$5:E8)) -> 9131 | G8: 0.8 | H8: =IF(E8="","",F8-C8) -> 465 | I8: =IF(E8="","à compléter",IF(H8>Budget!$I$15,"Alerte : réserve dépassée",IF(H8>0,"Dépassement (dans la réserve)","Dans le budget"))) -> Dépassement (dans la réserve)
A9: J5 ven | B9: =Budget!I10/2+Budget!I11+Budget!I12/5 -> 1774 | C9: =SUM($B$5:B9) -> 10440 | D9: =C9/Budget!$I$14 -> 1 | E9: 1774 | F9: =IF(E9="",NA(),SUM($E$5:E9)) -> 10905 | G9: 1 | H9: =IF(E9="","",F9-C9) -> 465 | I9: =IF(E9="","à compléter",IF(H9>Budget!$I$15,"Alerte : réserve dépassée",IF(H9>0,"Dépassement (dans la réserve)","Dans le budget"))) -> Dépassement (dans la réserve)
A10: Total | B10: =SUM(B5:B9) -> 10440 | E10: =SUM(E5:E9) -> 10905
A11: Budget total (avec réserve) | B11: =Budget!I16 -> 11484
A13: Les cellules jaunes (coût réel et avancement réel) sont remplies chaque soir pendant la semaine PPE. Le cumul, l'écart et le statut se calculent automatiquement.
A14: SIMULATION : formateur absent, les valeurs réelles (cellules jaunes) sont un cas plausible choisi par le chef de projet. Aléa simulé : administrateur système malade le J3.

Sheet Risques
A1: Principaux risques du projet
A2: De Sousa Nunes Alessandro - CFC 3
A4: ID | B4: Risque | C4: Proba. (1-5) | D4: Impact (1-5) | E4: Score | F4: Mesure prévue | G4: Responsable
A5: R1 | B5: La machine virtuelle n'est pas prête le J1 | C5: 2 | D5: 4 | E5: =C5*D5 -> 8 | F5: Demande faite avant la semaine, solution de secours sur un PC de test | G5: Admin système
A6: R2 | B6: Documents existants mal organisés, reprise plus longue que prévu | C6: 4 | D6: 3 | E6: =C6*D6 -> 12 | F6: Reprendre d'abord les documents les plus utilisés, le reste après le projet | G6: Référent métier
A7: R3 | B7: Référent métier peu disponible | C7: 3 | D7: 3 | E7: =C7*D7 -> 9 | F7: Réserver ses créneaux dès le J1 avec son responsable | G7: Chef de projet
A8: R4 | B8: Problème de connexion avec les comptes de l'entreprise | C8: 2 | D8: 3 | E8: =C8*D8 -> 6 | F8: Test de connexion dès le J2, connexion locale en solution de secours | G8: Développeur
A9: R5 | B9: Peu de participants à la formation | C9: 2 | D9: 2 | E9: =C9*D9 -> 4 | F9: Formation courte (30 min) et guide d'une page | G9: Chef de projet

Sheet RACI
A1: Matrice RACI - Mise en place du wiki interne
A2: De Sousa Nunes Alessandro - CFC 3
A4: Activité | B4: Sponsor | C4: Chef de projet | D4: Admin système | E4: Développeur | F4: Référent métier | G4: Utilisateurs | H4: Contrôle (un seul A)
A5: L1 - Cadrage et lancement | B5: A | C5: R | D5: C | E5: C | F5: C | G5: I | H5: =IF(COUNTIF(B5:G5,"A")=1,"OK","Erreur") -> OK
A6: L2 - Installation du serveur et du wiki | C6: A | D6: R | E6: I | H6: =IF(COUNTIF(B6:G6,"A")=1,"OK","Erreur") -> OK
A7: L3 - Configuration (droits, comptes) | C7: A | D7: R | E7: R | F7: C | H7: =IF(COUNTIF(B7:G7,"A")=1,"OK","Erreur") -> OK
A8: L4 - Reprise des documents | C8: A | E8: R | F8: R | G8: C | H8: =IF(COUNTIF(B8:G8,"A")=1,"OK","Erreur") -> OK
A9: L5 - Tests et recette | B9: I | C9: A | D9: R | E9: R | F9: R | G9: C | H9: =IF(COUNTIF(B9:G9,"A")=1,"OK","Erreur") -> OK
A10: L6 - Formation | B10: I | C10: A | D10: C | F10: R | G10: I | H10: =IF(COUNTIF(B10:G10,"A")=1,"OK","Erreur") -> OK
A11: L7 - Pilotage et reporting | B11: A | C11: R | D11: I | E11: I | F11: I | H11: =IF(COUNTIF(B11:G11,"A")=1,"OK","Erreur") -> OK
A12: Décisions du comité (réserve, aléa) | B12: A | C12: R | D12: C | E12: C | F12: C | H12: =IF(COUNTIF(B12:G12,"A")=1,"OK","Erreur") -> OK
A13: Mise en service et clôture | B13: A | C13: R | D13: R | E13: I | F13: C | G13: I | H13: =IF(COUNTIF(B13:G13,"A")=1,"OK","Erreur") -> OK
A15: R = Réalise le travail | A = Approuve, rend des comptes (un seul par activité) | C = Consulté avant | I = Informé après
